{"meta":{"total":2,"perPage":10,"page":1,"direction":"asc","sortBy":"name"},"records":[{"params":{"_id":"69d8b9cef7f434f777d453fc","course":"69d8b53399e9c062029e30b6","name":"English","slug":"english subject","description":"","status":"active","displayOrder":0,"totalQuestionCount":0,"questionDraftCount":0,"questionPublishedCount":0,"lastQuestionUploadAt":null,"createdAt":"2026-04-10T08:50:22.915Z","updatedAt":"2026-04-10T08:50:22.915Z","__v":0},"populated":{"course":{"params":{"_id":"69d8b53399e9c062029e30b6","name":"Bachelor of Science in Computer Science and Information Technology","slug":"bsc.csit","description":"","status":"active","createdAt":"2026-04-10T08:30:43.958Z","updatedAt":"2026-04-10T08:30:43.958Z","__v":0},"populated":{},"baseError":null,"errors":{},"id":"69d8b53399e9c062029e30b6","title":"Bachelor of Science in Computer Science and Information Technology","recordActions":[{"name":"show","actionType":"record","icon":"Monitor","label":"show","resourceId":"MockTestCourse","guard":"","showFilter":false,"showResourceActions":true,"showInDrawer":false,"hideActionHeader":false,"containerWidth":1,"layout":null,"variant":"default","parent":null,"hasHandler":true,"custom":{}},{"name":"edit","actionType":"record","icon":"Edit","label":"edit","resourceId":"MockTestCourse","guard":"","showFilter":false,"showResourceActions":true,"showInDrawer":false,"hideActionHeader":false,"containerWidth":1,"layout":null,"variant":"default","parent":null,"hasHandler":true,"custom":{}},{"name":"delete","actionType":"record","icon":"Trash2","label":"delete","resourceId":"MockTestCourse","guard":"confirmDelete","showFilter":false,"showResourceActions":true,"component":false,"showInDrawer":false,"hideActionHeader":false,"containerWidth":1,"layout":null,"variant":"danger","parent":null,"hasHandler":true,"custom":{}}],"bulkActions":[{"name":"bulkDelete","actionType":"bulk","icon":"Trash2","label":"bulkDelete","resourceId":"MockTestCourse","guard":"","showFilter":false,"showResourceActions":true,"showInDrawer":true,"hideActionHeader":false,"containerWidth":"500px","layout":null,"variant":"danger","parent":null,"hasHandler":true,"custom":{}}]}},"baseError":null,"errors":{},"id":"69d8b9cef7f434f777d453fc","title":"English","recordActions":[{"name":"show","actionType":"record","icon":"Monitor","label":"show","resourceId":"MockTestSubject","guard":"","showFilter":false,"showResourceActions":true,"showInDrawer":false,"hideActionHeader":false,"containerWidth":1,"layout":null,"variant":"default","parent":null,"hasHandler":true,"custom":{}},{"name":"edit","actionType":"record","icon":"Edit","label":"edit","resourceId":"MockTestSubject","guard":"","showFilter":false,"showResourceActions":true,"showInDrawer":false,"hideActionHeader":false,"containerWidth":1,"layout":null,"variant":"default","parent":null,"hasHandler":true,"custom":{}},{"name":"delete","actionType":"record","icon":"Trash2","label":"delete","resourceId":"MockTestSubject","guard":"confirmDelete","showFilter":false,"showResourceActions":true,"component":false,"showInDrawer":false,"hideActionHeader":false,"containerWidth":1,"layout":null,"variant":"danger","parent":null,"hasHandler":true,"custom":{}},{"name":"questionStudio","actionType":"record","icon":"Edit","label":"questionStudio","resourceId":"MockTestSubject","guard":"","showFilter":false,"showResourceActions":true,"component":"MockQuestionStudio","showInDrawer":false,"hideActionHeader":false,"containerWidth":1,"layout":null,"variant":"default","parent":null,"hasHandler":true,"custom":{}}],"bulkActions":[{"name":"bulkDelete","actionType":"bulk","icon":"Trash2","label":"bulkDelete","resourceId":"MockTestSubject","guard":"","showFilter":false,"showResourceActions":true,"showInDrawer":true,"hideActionHeader":false,"containerWidth":"500px","layout":null,"variant":"danger","parent":null,"hasHandler":true,"custom":{}}]},{"params":{"_id":"69d8b55399e9c062029e30bf","course":"69d8b53399e9c062029e30b6","name":"Math","slug":"mathematics","description":"","status":"active","displayOrder":0,"totalQuestionCount":0,"questionDraftCount":0,"questionPublishedCount":0,"lastQuestionUploadAt":null,"createdAt":"2026-04-10T08:31:15.107Z","updatedAt":"2026-04-10T08:31:15.107Z","__v":0},"populated":{"course":{"params":{"_id":"69d8b53399e9c062029e30b6","name":"Bachelor of Science in Computer Science and Information Technology","slug":"bsc.csit","description":"","status":"active","createdAt":"2026-04-10T08:30:43.958Z","updatedAt":"2026-04-10T08:30:43.958Z","__v":0},"populated":{},"baseError":null,"errors":{},"id":"69d8b53399e9c062029e30b6","title":"Bachelor of Science in Computer Science and Information Technology","recordActions":[{"name":"show","actionType":"record","icon":"Monitor","label":"show","resourceId":"MockTestCourse","guard":"","showFilter":false,"showResourceActions":true,"showInDrawer":false,"hideActionHeader":false,"containerWidth":1,"layout":null,"variant":"default","parent":null,"hasHandler":true,"custom":{}},{"name":"edit","actionType":"record","icon":"Edit","label":"edit","resourceId":"MockTestCourse","guard":"","showFilter":false,"showResourceActions":true,"showInDrawer":false,"hideActionHeader":false,"containerWidth":1,"layout":null,"variant":"default","parent":null,"hasHandler":true,"custom":{}},{"name":"delete","actionType":"record","icon":"Trash2","label":"delete","resourceId":"MockTestCourse","guard":"confirmDelete","showFilter":false,"showResourceActions":true,"component":false,"showInDrawer":false,"hideActionHeader":false,"containerWidth":1,"layout":null,"variant":"danger","parent":null,"hasHandler":true,"custom":{}}],"bulkActions":[{"name":"bulkDelete","actionType":"bulk","icon":"Trash2","label":"bulkDelete","resourceId":"MockTestCourse","guard":"","showFilter":false,"showResourceActions":true,"showInDrawer":true,"hideActionHeader":false,"containerWidth":"500px","layout":null,"variant":"danger","parent":null,"hasHandler":true,"custom":{}}]}},"baseError":null,"errors":{},"id":"69d8b55399e9c062029e30bf","title":"Math","recordActions":[{"name":"show","actionType":"record","icon":"Monitor","label":"show","resourceId":"MockTestSubject","guard":"","showFilter":false,"showResourceActions":true,"showInDrawer":false,"hideActionHeader":false,"containerWidth":1,"layout":null,"variant":"default","parent":null,"hasHandler":true,"custom":{}},{"name":"edit","actionType":"record","icon":"Edit","label":"edit","resourceId":"MockTestSubject","guard":"","showFilter":false,"showResourceActions":true,"showInDrawer":false,"hideActionHeader":false,"containerWidth":1,"layout":null,"variant":"default","parent":null,"hasHandler":true,"custom":{}},{"name":"delete","actionType":"record","icon":"Trash2","label":"delete","resourceId":"MockTestSubject","guard":"confirmDelete","showFilter":false,"showResourceActions":true,"component":false,"showInDrawer":false,"hideActionHeader":false,"containerWidth":1,"layout":null,"variant":"danger","parent":null,"hasHandler":true,"custom":{}},{"name":"questionStudio","actionType":"record","icon":"Edit","label":"questionStudio","resourceId":"MockTestSubject","guard":"","showFilter":false,"showResourceActions":true,"component":"MockQuestionStudio","showInDrawer":false,"hideActionHeader":false,"containerWidth":1,"layout":null,"variant":"default","parent":null,"hasHandler":true,"custom":{}}],"bulkActions":[{"name":"bulkDelete","actionType":"bulk","icon":"Trash2","label":"bulkDelete","resourceId":"MockTestSubject","guard":"","showFilter":false,"showResourceActions":true,"showInDrawer":true,"hideActionHeader":false,"containerWidth":"500px","layout":null,"variant":"danger","parent":null,"hasHandler":true,"custom":{}}]}]}